[
	{
		"name": "soHieuThucDia",
		"schemaProp": "soHieu",
		"label": "Số hiệu thực địa(*)",
		"required": true,
		"type": "String",
		"regex": "^.{1,100}$",
		"autoCompletion": false
	},
	{
		"name": "soHieuBaoTangCS",
		"schemaProp": "soHieu",
		"label": "Số hiệu Bảo tàng cơ sở (*)",
		"required": true,
		"type": "String",
		"regex": "^.{1,100}$",
		"autoCompletion": false
	},
	{
		"name": "soHieuBTTNVN",
		"schemaProp": "soHieu",
		"label": "Số hiệu BTTNVN",
		"required": false,
		"type": "String",
		"regex": "^.{0,100}$",
		"autoCompletion": false
	},
	{
		"name": "maKyHieuMauVatQuocTe",
		"schemaProp": "soHieu",
		"label": "Mã ký hiệu mẫu vật quốc tế",
		"required": false,
		"type": "String",
		"regex": "^.{0,100}$",
		"autoCompletion": false
	},
	{
		"name": "kyHieuMauVatKhac",
		"schemaProp": "soHieu",
		"label": "Các ký hiệu mẫu vật khác",
		"required": false,
		"type": "String",
		"regex": "^.{0,100}$",
		"autoCompletion": false
	},
	{
		"name": "thongTinKhac1",
		"schemaProp": "soHieu",
		"label": "Thông tin khác",
		"required": false,
		"type": "String"
	},
	{
		"name": "tenVietNam",
		"schemaProp": "tenMau",
		"label": "Tên Việt Nam (phổ thông) (*)",
		"required": true,
		"type": "String",
		"regex": "^.{1,100}$",
		"autoCompletion": false
	},
	{
		"name": "tenDiaPhuong",
		"schemaProp": "tenMau",
		"label": "Tên địa phương",
		"required": false,
		"type": "String",
		"regex": "^.{0,100}$",
		"autoCompletion": false
	},
	{
		"name": "tenTiengAnh",
		"schemaProp": "tenMau",
		"label": "Tên tiếng Anh",
		"required": false,
		"type": "String",
		"regex": "^.{0,100}$",
		"autoCompletion": false
	},
	{
		"name": "tenTheoBaoTang",
		"schemaProp": "tenMau",
		"label": "Tên mẫu vật theo hệ thống phân loại của Bảo tàng",
		"required": false,
		"type": "String",
		"regex": "^.{0,100}$",
		"autoCompletion": false
	},
	{
		"name": "tenKhoaHoc",
		"schemaProp": "tenMau",
		"label": "Tên khoa học (tên latinh)",
		"required": false,
		"type": "String",
		"regex": "^.{0,100}$",
		"autoCompletion": true
	},
	{
		"name": "nguoiDinhTen",
		"schemaProp": "tenMau",
		"label": "Người định tên",
		"required": false,
		"type": "String",
		"regex": "^.{0,100}$",
		"autoCompletion": false
	},
	{
		"name": "thongTinKhac2",
		"schemaProp": "duLieuThuMau",
		"label": "Thông tin khác",
		"required": false,
		"type": "String"
	},
	{
		"name": "soLuongMauVat",
		"schemaProp": "soLuongChatLuong",
		"label": "Số lượng mẫu vật",
		"required": false,
		"type": "Number",
		"regex": "^.{0,100}$",
		"autoCompletion": false
	},
	{
		"name": "soLuongTieuBan",
		"schemaProp": "soLuongChatLuong",
		"label": "Số lượng tiêu bản",
		"required": false,
		"type": "Number",
		"regex": "^.{0,100}$",
		"autoCompletion": false
	},
	{
		"name": "loaiMau",
		"schemaProp": "soLuongChatLuong",
		"label": "Loại mẫu vật",
		"required": false,
		"type": "String",
		"regex": "^.{0,100}$",
		"autoCompletion": false
	},
	{
		"name": "kichThuocMau",
		"schemaProp": "soLuongChatLuong",
		"label": "Kích thước mẫu vật (dài x rộng x cao) (*)",
		"required": true,
		"type": "String",
		"regex": "^.{1,100}$",
		"autoCompletion": false
	},
	{
		"name": "tinhTrangMau",
		"schemaProp": "soLuongChatLuong",
		"label": "Tình trạng mẫu vật (*)",
		"required": true,
		"type": "String",
		"regex": "^.{1,100}$",
		"autoCompletion": false
	},
	{
		"name": "thongTinKhac3",
		"schemaProp": "soLuongChatLuong",
		"label": "Thông tin khác",
		"required": false,
		"type": "String"
	},
	{
		"name": "thoiGianThuMau",
		"schemaProp": "duLieuThuMau",
		"label": "Thời gian thu mẫu (*)",
		"required": true,
		"type": "Date",
		"regex": "^.{0,100}$",
		"autoCompletion": false
	},
	{
		"name": "nguoiThuMau",
		"schemaProp": "duLieuThuMau",
		"label": "Người thu mẫu (*)",
		"required": true,
		"type": "String",
		"regex": "^.{1,100}$",
		"autoCompletion": false
	},
	{
		"name": "coQuanThuMau",
		"schemaProp": "duLieuThuMau",
		"label": "Cơ quan thu mẫu",
		"required": false,
		"type": "String",
		"regex": "^.{0,100}$",
		"autoCompletion": true
	},
	{
		"name": "phuongPhapThuMau",
		"schemaProp": "duLieuThuMau",
		"label": "Phương pháp thu mẫu",
		"required": true,
		"type": "String",
		"regex": "^.{1,100}$"
	},
	{
		"name": "quocGia",
		"schemaProp": "duLieuThuMau.diaDiemThuMau",
		"label": "Quốc gia (*)",
		"required": true,
		"type": "String",
		"regex": "^.{1,100}$",
		"autoCompletion": true
	},
	{
		"name": "tinh",
		"schemaProp": "duLieuThuMau.diaDiemThuMau",
		"label": "Tỉnh (*)",
		"required": true,
		"type": "String",
		"regex": "^.{1,100}$",
		"autoCompletion": true
	},
	{
		"name": "huyen",
		"schemaProp": "duLieuThuMau.diaDiemThuMau",
		"label": "Huyện (*)",
		"required": true,
		"type": "String",
		"regex": "^.{1,100}$",
		"autoCompletion": true
	},
	{
		"name": "xa",
		"schemaProp": "duLieuThuMau.diaDiemThuMau",
		"label": "Xã (*)",
		"required": true,
		"type": "String",
		"regex": "^.{1,100}$",
		"autoCompletion": true
	},
	{
		"name": "thon",
		"schemaProp": "duLieuThuMau.diaDiemThuMau",
		"label": "Thôn/bản",
		"required": true,
		"type": "String",
		"regex": "^.{1,100}$",
		"autoCompletion": true
	},
	{
		"name": "viDo",
		"schemaProp": "duLieuThuMau.viTriToaDo",
		"label": "Vĩ độ N(*)",
		"required": true,
		"type": "String",
		"regex": "^.{0,100}$",
		"autoCompletion": false
	},
	{
		"name": "kinhDo",
		"schemaProp": "duLieuThuMau.viTriToaDo",
		"label": "Kinh độ E (*)",
		"required": true,
		"type": "String",
		"regex": "^.{0,100}$",
		"autoCompletion": false
	},
	{
		"name": "thongTinDuAn",
		"schemaProp": "duLieuThuMau",
		"label": "Thông tin về Dự án, đề tài/chuyến/đợt thu thập mẫu vật (*)",
		"required": false,
		"type": "String",
		"regex": "^.{0,100}$",
		"autoCompletion": false
	},
	{
		"name": "ghiChepThucDia",
		"schemaProp": "duLieuThuMau",
		"label": "Ghi chép thực địa (*)",
		"required": true,
		"type": "String",
		"regex": "^.{1,100}$",
		"autoCompletion": false
	},
	{
		"name": "banDo",
		"schemaProp": "duLieuThuMau",
		"label": "Bản đồ",
		"required": true,
		"type": "File",
		"regex": "^.+\\.(pdf|docx?)$",
		"autoCompletion": false
	},
	{
		"name": "thongTinKhac4",
		"schemaProp": "duLieuThuMau",
		"label": "Thông tin khác",
		"required": false,
		"type": "String"
	},
	{
		"name": "thoiGianPhanTich",
		"schemaProp": "duLieuPhanTichMau",
		"label": "Thời gian phân tích/giám định/định loại mẫu",
		"required": false,
		"type": "Date",
		"regex": "^.{0,100}$",
		"autoCompletion": false
	},
	{
		"name": "nguoiPhanTich",
		"schemaProp": "duLieuPhanTichMau",
		"label": "Người phân tích/giám định/định loại mẫu (*)",
		"required": true,
		"type": "String",
		"regex": "^.{0,100}$",
		"autoCompletion": false
	},
	{
		"name": "coQuanToChucPhanTich",
		"schemaProp": "duLieuPhanTichMau",
		"label": "Cơ quan/tổ chức phân tích/giám định/phân loại mẫu (*)",
		"required": true,
		"type": "String",
		"regex": "^.{1,100}$",
		"autoCompletion": true
	},
	{
		"name": "taiLieuPhanTich",
		"schemaProp": "duLieuPhanTichMau",
		"label": "Tài liệu phân tích/giám định/phân loại đi kèm (*)",
		"required": true,
		"type": "File",
		"regex": "^.+\\.(pdf|docx?)$",
		"autoCompletion": false
	},
	{
		"name": "phanTichQuangHoc",
		"schemaProp": "media",
		"label": "Các phân tích quang học",
		"required": false,
		"type": "Mixed",
		"subProps": ["phanTichQuangHocStr", "phanTichQuangHocFile"]
	},
	{
		"name": "phanTichQuangHocStr",
		"schemaProp": "duLieuPhanTichMau",
		"label": "Các phân tích quang học",
		"required": false,
		"type": "String",
		"regex": "^.{0,100}$",
		"autoCompletion": false
	},
	{
		"name": "phanTichQuangHocFile",
		"schemaProp": "duLieuPhanTichMau",
		"label": "Các phân tích quang học",
		"required": false,
		"type": "File",
		"regex": "^.+\\.(jpe?g|gif|png|pdf|docx?)$",
		"autoCompletion": false
	},
	{
		"name": "ketQuaThanhPhanVatChat",
		"schemaProp": "duLieuPhanTichMau",
		"label": "Các kết quả phân tích thành phần vật chất",
		"required": false,
		"type": "File",
		"regex": "^.+\\.(pdf|docx?)$",
		"autoCompletion": false
	},
	{
		"name": "ketQuaPhanTichDongVi",
		"schemaProp": "duLieuPhanTichMau",
		"label": "Kết quả phân tích đồng vị và định tuổi",
		"required": false,
		"type": "File",
		"regex": "^.+\\.(pdf|docx?)$",
		"autoCompletion": false
	},
	{
		"name": "phanTichKhac",
		"schemaProp": "duLieuPhanTichMau",
		"label": "Các phân tích khác",
		"required": false,
		"type": "File",
		"regex": "^.+\\.(jpe?g|gif|png|pdf|docx?)$",
		"autoCompletion": false
	},
	{
		"name": "dacDiemDiaChat",
		"schemaProp": "duLieuPhanTichMau",
		"label": "-Đặc điểm địa chất",
		"required": false,
		"type": "String",
		"regex": "^.{0,100}$",
		"autoCompletion": false
	},
	{
		"name": "loaiHinhNguonGoc",
		"schemaProp": "duLieuPhanTichMau",
		"label": "-Loại hình nguồn gốc",
		"required": false,
		"type": "String",
		"regex": "^.{0,100}$",
		"autoCompletion": false
	},
	{
		"name": "thongTinKhac5",
		"schemaProp": "duLieuPhanTichMau",
		"label": "Thông tin khác",
		"required": false,
		"type": "String"
	},
	{
		"name": "anhMauVat",
		"schemaProp": "media",
		"label": "Ảnh mẫu vật (*)",
		"required": true,
		"type": "File",
		"regex": "^.+\\.(jpe?g|gif|png|pdf|docx?)$",
		"autoCompletion": false
	},
	{
		"name": "hinhAnhNgoaiThucDia",
		"schemaProp": "media",
		"label": "Hình ảnh mẫu vật ngoài thực địa",
		"required": false,
		"type": "File",
		"regex": "^.+\\.(jpe?g|gif|png|pdf|docx?)$",
		"autoCompletion": false
	},
	{
		"name": "video",
		"schemaProp": "media",
		"label": "Thông tin về phim, video",
		"required": false,
		"type": "Mixed",
		"subProps": ["videoStr", "videoFile"]
	},
	{
		"name": "videoStr",
		"schemaProp": "media",
		"label": "Thông tin về phim, video",
		"required": false,
		"type": "String",
		"regex": "^.{0,100}$",
		"autoCompletion": false
	},
	{
		"name": "videoFile",
		"schemaProp": "media",
		"label": "Thông tin về phim, video",
		"required": false,
		"type": "File",
		"regex": "^.+\\.(mp4|flv|mpg)$",
		"autoCompletion": false
	},
	{
		"name": "hinhAnhDinhKem",
		"schemaProp": "media.xuLyCheTac",
		"label": "Hình ảnh đính kèm Xử lý chế tác",
		"required": false,
		"type": "File",
		"regex": "^.+\\.(jpe?g|gif|png|pdf|docx?)$",
		"autoCompletion": false
	},
	{
		"name": "phuongThucXuLy",
		"schemaProp": "media.xuLyCheTac",
		"label": "Phương thức xử lý chế tác",
		"required": false,
		"type": "String",
		"regex": "^.{0,100}$",
		"autoCompletion": false
	},
	{
		"name": "nguoiXuLy",
		"schemaProp": "media.xuLyCheTac",
		"label": "Người xử lý, chế tác mẫu",
		"required": false,
		"type": "String",
		"regex": "^.{0,100}$",
		"autoCompletion": false
	},
	{
		"name": "coQuanXuLy",
		"schemaProp": "media.xuLyCheTac",
		"label": "Cơ quan xử lý, chế tác mẫu",
		"required": false,
		"type": "String",
		"regex": "^.{0,100}$",
		"autoCompletion": false
	},
	{
		"name": "anhMauSauCheTac",
		"schemaProp": "media.xuLyCheTac",
		"label": "Ảnh mẫu sau chế tác",
		"required": false,
		"type": "File",
		"regex": "^.+\\.(jpe?g|gif|png|pdf|docx?)$",
		"autoCompletion": false
	},
	{
		"name": "thongTinKhac6",
		"schemaProp": "media",
		"label": "Thông tin khác",
		"required": false,
		"type": "String"
	},
	{
		"name": "loaiMau",
		"schemaProp": "dacDiemMauVat",
		"label": "Loại mẫu(*)",
		"required": true,
		"type": "String",
		"regex": "^.{0,100}$",
		"autoCompletion": false
	},
	{
		"name": "hinhDangMauTonTai",
		"schemaProp": "dacDiemMauVat",
		"label": "Hình dáng mẫu, dạng tồn tại (*)",
		"required": true,
		"type": "String",
		"regex": "^.{0,100}$",
		"autoCompletion": false
	},
	{
		"name": "mauSac",
		"schemaProp": "dacDiemMauVat",
		"label": "Màu sắc (*)",
		"required": true,
		"type": "String",
		"regex": "^.{0,100}$",
		"autoCompletion": false
	},
	{
		"name": "phanLoaiSuDung",
		"schemaProp": "dacDiemMauVat",
		"label": "Phân loại sử dụng mẫu",
		"required": false,
		"type": "String",
		"regex": "^.{0,100}$",
		"autoCompletion": false
	},
	{
		"name": "thanhPhanKhoangVat",
		"schemaProp": "dacDiemMauVat",
		"label": "Thành phần khoáng vật (*)",
		"required": true,
		"type": "String",
		"regex": "^.{0,100}$",
		"autoCompletion": false
	},
	{
		"name": "tinhChatVatLy",
		"schemaProp": "dacDiemMauVat",
		"label": "Tính chất vật lý (*)",
		"required": true,
		"type": "String",
		"regex": "^.{0,100}$",
		"autoCompletion": false
	},
	{
		"name": "linhVucSuDung",
		"schemaProp": "dacDiemMauVat",
		"label": "Lĩnh vực sử dụng",
		"required": false,
		"type": "String",
		"regex": "^.{0,100}$",
		"autoCompletion": false
	},
	{
		"name": "dacDiemPhanBo",
		"schemaProp": "dacDiemMauVat",
		"label": "Đặc điểm phân bố (ở Việt Nam và trên thế giới)",
		"required": false,
		"type": "String",
		"regex": "^.{0,100}$",
		"autoCompletion": false
	},
	{
		"name": "congThucHoaHoc",
		"schemaProp": "dacDiemMauVat",
		"label": "Công thức hóa học",
		"required": false,
		"type": "File",
		"regex": "^.+\\.(pdf|docx?)$",
		"autoCompletion": false
	},
	{
		"name": "thanhPhanHoaHoc",
		"schemaProp": "dacDiemMauVat",
		"label": "Thành phần hoá học",
		"required": false,
		"type": "String",
		"regex": "^.{0,100}$",
		"autoCompletion": false
	},
	{
		"name": "thongTinKhac7",
		"schemaProp": "dacDiemMauVat",
		"label": "Thông tin khác",
		"required": false,
		"type": "String"
	},
	{
		"name": "ngayNhapMau",
		"schemaProp": "luuTruBaoQuan",
		"label": "Ngày nhập mẫu",
		"required": false,
		"type": "Date",
		"regex": "^.{0,100}$",
		"autoCompletion": false
	},
	{
		"name": "nguoiGiao",
		"schemaProp": "luuTruBaoQuan",
		"label": "Người giao mẫu",
		"required": false,
		"type": "String",
		"regex": "^.{0,100}$",
		"autoCompletion": false
	},
	{
		"name": "nguoiNhan",
		"schemaProp": "luuTruBaoQuan",
		"label": "Người nhận mẫu",
		"required": false,
		"type": "String",
		"regex": "^.{0,100}$",
		"autoCompletion": false
	},
	{
		"name": "coQuanNhapVatMau",
		"schemaProp": "luuTruBaoQuan",
		"label": "Cơ quan nhập mẫu",
		"required": false,
		"type": "String",
		"regex": "^.{0,100}$",
		"autoCompletion": true
	},
	{
		"name": "hinhThucNhapMau",
		"schemaProp": "luuTruBaoQuan",
		"label": "Hình thức nhập mẫu",
		"required": false,
		"type": "String",
		"regex": "^.{0,100}$",
		"autoCompletion": false
	},
	{
		"name": "traoDoiMau",
		"schemaProp": "luuTruBaoQuan",
		"label": "Trao đổi mẫu",
		"required": false,
		"type": "String",
		"regex": "^.{0,100}$",
		"autoCompletion": false
	},
	{
		"name": "vayMuon",
		"schemaProp": "luuTruBaoQuan",
		"label": "Vay mượn mẫu",
		"required": false,
		"type": "String",
		"regex": "^.{0,100}$",
		"autoCompletion": false
	},
	{
		"name": "khuLuuTruMau",
		"schemaProp": "luuTruBaoQuan",
		"label": "Khu lưu trữ mẫu",
		"required": false,
		"type": "String",
		"regex": "^.{0,100}$",
		"autoCompletion": false
	},
	{
		"name": "noiLuuTru",
		"schemaProp": "luuTruBaoQuan",
		"label": "Nơi lưu giữ mẫu",
		"required": false,
		"type": "String",
		"regex": "^.{0,100}$",
		"autoCompletion": false
	},
	{
		"name": "giayPhepNhapMau",
		"schemaProp": "luuTruBaoQuan",
		"label": "Giấy phép nhập mẫu",
		"required": false,
		"type": "File",
		"regex": "^.+\\.(jpe?g|gif|png|pdf|docx?)$",
		"autoCompletion": false
	},
	{
		"name": "hoSoNhapMauVatDiKem",
		"schemaProp": "luuTruBaoQuan",
		"label": "Hồ sơ nhập mẫu vật đi kèm",
		"required": false,
		"type": "File",
		"regex": "^.+\\.(jpe?g|gif|png|pdf|docx?)$",
		"autoCompletion": false
	},
	{
		"name": "nguoiNhapPhieuMauVat",
		"schemaProp": "luuTruBaoQuan",
		"label": "Người lập phiếu mẫu vật (*)",
		"required": false,
		"type": "String",
		"regex": "^.{0,100}$",
		"autoCompletion": false
	},
	{
		"name": "nguoiNhapVaoPhanMem",
		"schemaProp": "luuTruBaoQuan",
		"label": "Người nhập thông tin vào phần mềm",
		"required": false,
		"type": "String",
		"regex": "^.{0,100}$",
		"autoCompletion": false
	},
	{
		"name": "thongTinKhac8",
		"schemaProp": "luuTruBaoQuan",
		"label": "Thông tin khác",
		"required": false,
		"type": "String"
	},
	{
		"name": "thongTinKhac9",
		"schemaProp": "thongTinKhac",
		"label": "Thông tin khác",
		"required": false,
		"type": "String",
		"regex": "^.{0,100}$",
		"autoCompletion": false
	},
	{
		"name": "maDeTai",
		"schemaProp": "maDeTai",
		"label": "Mã đề tài",
		"required": true,
		"type": "String"
	},
	
	{
		"name": "soHieu",
		"type": "Metadata",
		"label": "Số hiệu mẫu vật"
	},
	{
		"name": "tenMau",
		"type": "Metadata",
		"label": "Tên mẫu vật"
	},
	{
		"name": "soLuongChatLuong",
		"type": "Metadata",
		"label": "Số lượng và chất lượng mẫu vật"
	},
	{
		"name": "duLieuThuMau",
		"type": "Metadata",
		"label": "Nhóm dữ liệu Thu mẫu"
	},
	{
		"name": "duLieuPhanTichMau",
		"type": "Metadata",
		"label": "Nhóm dữ liệu Phân tích mẫu/Giám định mẫu"
	},
	{
		"name": "media",
		"type": "Metadata",
		"label": "Nhóm dữ liệu Hình ảnh/phim, tài liệu mẫu vật"
	},
	{
		"name": "phanBoVaSuDung",
		"type": "Metadata",
		"label": "Nhóm dữ liệu Phân bố và giá trị sử dụng"
	},
	{
		"name": "luuTruBaoQuan",
		"type": "Metadata",
		"label": "Nhóm dữ liệu Lưu trữ, bảo quản mẫu vật"
	},
	{
		"name": "thongTinKhac",
		"type": "Metadata",
		"label": "Nhóm dữ liệu thông tin khác"
	}
]